openai_pygenerator/__init__.py
openai_pygenerator/example.py
openai_pygenerator/openai_pygenerator.py
openai_pygenerator/py.typed
openai_pygenerator-0.6.2.dist-info/LICENSE.txt
openai_pygenerator-0.6.2.dist-info/METADATA
openai_pygenerator-0.6.2.dist-info/WHEEL
openai_pygenerator-0.6.2.dist-info/RECORD
