Metadata-Version: 2.1
Name: openai-pygenerator
Version: 0.6.2
Summary: Simple generator wrapper for OpenAI Python API with retry
License: MIT
Author: Steve Phelps
Author-email: phelps.sg@gmail.com
Requires-Python: >=3.8.1,<4.0.0
Classifier: License :: OSI Approved :: MIT License
Classifier: Programming Language :: Python :: 3
Classifier: Programming Language :: Python :: 3.9
Classifier: Programming Language :: Python :: 3.10
Classifier: Programming Language :: Python :: 3.11
Classifier: Programming Language :: Python :: 3.12
Requires-Dist: openai (>=1.0.0,<2.0.0)
